Workbook

Sheet Research Log
A1: PAXA — Product Research Tracker
A2: Date | B2: Product Name | C2: URL | D2: Platform | E2: Target Market | F2: Sell Price ($) | G2: COGS ($) | H2: Shipping ($) | I2: Gross Margin % | J2: BE ROAS | K2: Est Net Margin | L2: VERDICT | M2: P1 Problem Clarity | N2: P2 Visual Before/After | O2: P3 Marketing Angles | P2: P4 Trend Timing | Q2: P5 Brand Competition | R2: P6 Organic Content | S2: Angle 1 | T2: Angle 2 | U2: Angle 3 | V2: Notes / Risks
A3: 2026-04-06 | B3: Portable Neck Massager | C3: https://aliexpress.com/item/123 | D3: AliExpress | E3: UK | F3: 39 | G3: 8 | H3: 4 | I3: =(F3-G3-H3)/F3 -> 0.69230769 | J3: =F3/(F3-G3-H3) -> 1.4444444 | K3: =(F3-G3-H3)*0.82/F3 -> 0.56769231 | L3: PASS | M3: PASS | N3: PASS | O3: PASS | P3: WARN | Q3: PASS | R3: PASS | S3: Your neck is destroying your focus — fix it in 15 mins | T3: Why office workers are buying this instead of physio | U3: The £8 gadget that replaces £60 physio sessions | V3: Check CE certification for UK market
A4: 2026-04-06 | B4: LED Eyelash Curler | C4: https://tiktokshop.com/item/456 | D4: TikTok Shop | E4: UK | F4: 24 | G4: 5 | H4: 3 | I4: =(F4-G4-H4)/F4 -> 0.66666667 | J4: =F4/(F4-G4-H4) -> 1.5 | K4: =(F4-G4-H4)*0.82/F4 -> 0.54666667 | L4: REVIEW | M4: PASS | N4: FAIL | O4: WARN | P4: PASS | Q4: FAIL | R4: WARN | S4: The tool makeup artists don't want you to know about | V4: Market saturating — 40+ stores running ads
A5: 2026-04-07 | B5: Dog Calming Spray | C5: https://shopify-store.com/product/789 | D5: Shopify | E5: UK | F5: 29 | G5: 6 | H5: 3.5 | I5: =(F5-G5-H5)/F5 -> 0.67241379 | J5: =F5/(F5-G5-H5) -> 1.4871795 | K5: =(F5-G5-H5)*0.82/F5 -> 0.55137931 | L5: FAIL | M5: PASS | N5: WARN | O5: FAIL | P5: FAIL | Q5: PASS | R5: WARN | V5: Dominated by Adaptil brand — no differentiation angle
A6: 2026-04-10 | B6: Snuffle Mat (Enrichment) | C6: https://amazon.co.uk/s?k=snuffle+mat+dog | D6: Amazon UK | E6: UK | F6: 18 | G6: 4 | H6: 4 | I6: =(F6-G6-H6)/F6 -> 0.55555556 | J6: =F6/(F6-G6-H6) -> 1.8 | K6: =(F6-G6-H6)*0.82/F6 -> 0.45555556 | L6: FAIL | M6: PASS | N6: PASS | O6: WARN | P6: WARN | Q6: FAIL | R6: WARN | S6: Your dog's nose needs to work before you leave — sniffing depletes cortisol | T6: The 10-minute pre-departure ritual that changes your dog's stress response | V6: DISCARD — P5 FAIL. Amazon saturated: 500+ sellers, top listings 4k+ reviews. No differentiation angle available. UK market spread thin on margin.
A7: 2026-04-10 | B7: Premium Lick Mat (Suction Cup Silicone) — Single Unit | C7: https://www.aliexpress.com/wholesale?SearchText=dog+lick+mat+suction+silicone | D7: AliExpress | E7: UK | F7: 20 | G7: 2.5 | H7: 5.5 | I7: =(F7-G7-H7)/F7 -> 0.6 | J7: =F7/(F7-G7-H7) -> 1.6666667 | K7: =(F7-G7-H7)*0.82/F7 -> 0.492 | L7: WARN | M7: PASS | N7: PASS | O7: PASS | P7: PASS | Q7: WARN | R7: PASS | S7: The tool that defuses your dog's departure panic before it starts | T7: Most owners leave toys when they go out — this is the only one that actually rewires anxiety | U7: Why licking is the single most powerful counter-conditioning trigger your dog has | V7: UPDATED WITH REAL NUMBERS (April 2026). Supplier confirmed: 140 units @ £2.50/unit. Shipping: Royal Mail Tracked 48 @ £3.65. 3PL: Bezos.ai or Airbox (pick/pack £1.85/order, storage £0.15/unit/mo). TOTAL COST PER ORDER: £7.65 (COGS £2.50 + ship £3.65 + pick/pack £1.85). GROSS MARGIN: 60% — BELOW 65% target. Single unit not viable for paid ads. SOLUTION: Launch as bundle (2x mats for £35) — margin jumps to 70%. See row below. Meta CPA benchmark: £8-12. TikTok CPA benchmark: £6-9. 3PL rec: Bezos.ai or Airbox. Shipping rec: Royal Mail Tracked 48.
A8: 2026-04-12 | B8: PAXA Lick Mat BUNDLE (2x for £35) | C8: https://www.aliexpress.com/wholesale?SearchText=dog+lick+mat+suction+silicone | D8: AliExpress | E8: UK | F8: 35 | G8: 5 | H8: 5.5 | I8: =(F8-G8-H8)/F8 -> 0.7 | J8: =F8/(F8-G8-H8) -> 1.4285714 | K8: =(F8-G8-H8)*0.82/F8 -> 0.574 | L8: PASS | M8: PASS | N8: PASS | O8: PASS | P8: PASS | Q8: WARN | R8: PASS | S8: Shipping 2 mats costs the same as 1 — margin jumps from 60% to 70% | T8: At £35 bundle, max CPA is £24.50 — Meta's £8-12 CPA becomes comfortable | U8: TikTok Shop creator affiliate at 15-20% = £5.25-7 commission — still profitable | V8: PRIORITY LAUNCH FORMAT. Bundle mechanics: 2x lick mats for £35 (single = £20, bundle saves £5). COGS: £5.00 (2x £2.50). Ship + fulfilment: £5.50 (same weight class as single). GROSS MARGIN: 70% — above 65% target. BE ROAS: 1.43x. Meta CPA headroom: £24.50 max vs £8-12 benchmark = £12-16 profit per sale. TikTok Shop: 15-20% creator commission = £5.25-7 cost — still leaves £17-19 margin. Recommendation: Launch bundle as primary offer. Single unit as entry/upsell.
A9: 2026-04-10 | B9: Interactive Puzzle Feeder (Level 2) | C9: https://www.aliexpress.com/wholesale?SearchText=dog+puzzle+feeder+interactive+level+2 | D9: AliExpress | E9: UK | F9: 27 | G9: 5 | H9: 4 | I9: =(F8-G8-H8)/F8 -> 0.7 | J9: =F8/(F8-G8-H8) -> 1.4285714 | K9: =(F8-G8-H8)*0.82/F8 -> 0.574 | L9: REVIEW | M9: PASS | N9: PASS | O9: WARN | P9: WARN | Q9: WARN | R9: PASS | S9: A mentally depleted dog cannot sustain separation anxiety — this is the science | T9: Feed your dog's brain before you leave — 10 minutes of this equals a 45-minute walk | V9: REVIEW — P3 + P4 WARNs. 135 Amazon competitors (Nina Ottosson, KONG dominant). Gross margin 66.7% at £27. Differentiation angle possible via PAXA protocol framing (pre-departure cognitive depletion) but crowded content space. Proceed only if lick mat sourcing fails.
A10: 2026-04-10 | B10: Dog Bolster Calming Bed (Safe Space) | C10: https://www.aliexpress.com/wholesale?SearchText=dog+calming+donut+bed+bolster | D10: AliExpress | E10: UK | F10: 35 | G10: 9 | H10: 6 | I10: =(F9-G9-H9)/F9 -> 0.66666667 | J10: =F9/(F9-G9-H9) -> 1.5 | K10: =(F9-G9-H9)*0.82/F9 -> 0.54666667 | L10: REVIEW | M10: WARN | N10: PASS | O10: WARN | P10: PASS | Q10: WARN | R10: PASS | S10: Your dog doesn't have a safe place — that's why they can't self-regulate | T10: Foundation Phase of every separation anxiety protocol starts here | V10: REVIEW — Brand conflict risk: PAXA positions against "symptom masking" products. Calming bed is a symptom product. Only viable if positioned as PROTOCOL TOOL for Phase 1 foundation (safe place training). Gross margin 57.1% at £35 — BELOW 65% target. Raise to £40: margin 62.5% still WARN. Financial barrier. Deprioritise.
I11: =IF(F10>0,(F10-G10-H10)/F10,"") -> 0.57142857 | J11: =IF(F10>0,F10/(F10-G10-H10),"") -> 1.75 | K11: =IF(F10>0,(F10-G10-H10)*0.82/F10,"") -> 0.46857143
I12: =IF(F11>0,(F11-G11-H11)/F11,"") | J12: =IF(F11>0,F11/(F11-G11-H11),"") | K12: =IF(F11>0,(F11-G11-H11)*0.82/F11,"")
I13: =IF(F12>0,(F12-G12-H12)/F12,"") | J13: =IF(F12>0,F12/(F12-G12-H12),"") | K13: =IF(F12>0,(F12-G12-H12)*0.82/F12,"")
I14: =IF(F13>0,(F13-G13-H13)/F13,"") | J14: =IF(F13>0,F13/(F13-G13-H13),"") | K14: =IF(F13>0,(F13-G13-H13)*0.82/F13,"")
I15: =IF(F14>0,(F14-G14-H14)/F14,"") | J15: =IF(F14>0,F14/(F14-G14-H14),"") | K15: =IF(F14>0,(F14-G14-H14)*0.82/F14,"")
I16: =IF(F15>0,(F15-G15-H15)/F15,"") | J16: =IF(F15>0,F15/(F15-G15-H15),"") | K16: =IF(F15>0,(F15-G15-H15)*0.82/F15,"")
I17: =IF(F16>0,(F16-G16-H16)/F16,"") | J17: =IF(F16>0,F16/(F16-G16-H16),"") | K17: =IF(F16>0,(F16-G16-H16)*0.82/F16,"")
I18: =IF(F17>0,(F17-G17-H17)/F17,"") | J18: =IF(F17>0,F17/(F17-G17-H17),"") | K18: =IF(F17>0,(F17-G17-H17)*0.82/F17,"")
I19: =IF(F18>0,(F18-G18-H18)/F18,"") | J19: =IF(F18>0,F18/(F18-G18-H18),"") | K19: =IF(F18>0,(F18-G18-H18)*0.82/F18,"")
I20: =IF(F19>0,(F19-G19-H19)/F19,"") | J20: =IF(F19>0,F19/(F19-G19-H19),"") | K20: =IF(F19>0,(F19-G19-H19)*0.82/F19,"")
I21: =IF(F20>0,(F20-G20-H20)/F20,"") | J21: =IF(F20>0,F20/(F20-G20-H20),"") | K21: =IF(F20>0,(F20-G20-H20)*0.82/F20,"")
I22: =IF(F21>0,(F21-G21-H21)/F21,"") | J22: =IF(F21>0,F21/(F21-G21-H21),"") | K22: =IF(F21>0,(F21-G21-H21)*0.82/F21,"")
... I26: =IF(F25>0,(F25-G25-H25)/F25,"") | J26: =IF(F25>0,F25/(F25-G25-H25),"") | K26: =IF(F25>0,(F25-G25-H25)*0.82/F25,"")

Sheet Dashboard
A1: PAXA — Product Research Dashboard
B3: Total Analysed | D3: PASS | F3: REVIEW | H3: FAIL
B4: =COUNTA('Research Log'!B3:B1000) -> 8 | D4: =COUNTIF('Research Log'!L3:L1000,"PASS") -> 2 | F4: =COUNTIF('Research Log'!L3:L1000,"REVIEW") -> 3 | H4: =COUNTIF('Research Log'!L3:L1000,"FAIL") -> 2
B6: Financial Averages
B7: Avg Gross Margin | D7: =AVERAGEIF('Research Log'!L3:L1000,"PASS",'Research Log'!I3:I1000) -> 0.69615385
B8: Avg Break-Even ROAS | D8: =AVERAGE('Research Log'!J3:J1000) -> 1.5561593
B9: Avg Net Margin | D9: =AVERAGE('Research Log'!K3:K1000) -> 0.53072577
B10: Pass Rate | D10: =IF(COUNTA('Research Log'!B3:B1000)>0,COUNTIF('Research Log'!L3:L1000,"PASS")/COUNTA('Research Log'!B3:B1000),"") -> 0.25
B12: Recent Research (last 5)
B13: Date | C13: Product | D13: Platform | E13: Price | F13: Gross Margin | G13: BE ROAS | H13: Verdict
B14: ='Research Log'!A3 -> 2026-04-06 | C14: ='Research Log'!B3 -> Portable Neck Massager | D14: ='Research Log'!D3 -> AliExpress | E14: ='Research Log'!F3 -> 39 | F14: ='Research Log'!I3 -> 0.69230769 | G14: ='Research Log'!J3 -> 1.4444444 | H14: ='Research Log'!L3 -> PASS
B15: ='Research Log'!A4 -> 2026-04-06 | C15: ='Research Log'!B4 -> LED Eyelash Curler | D15: ='Research Log'!D4 -> TikTok Shop | E15: ='Research Log'!F4 -> 24 | F15: ='Research Log'!I4 -> 0.66666667 | G15: ='Research Log'!J4 -> 1.5 | H15: ='Research Log'!L4 -> REVIEW
B16: ='Research Log'!A5 -> 2026-04-07 | C16: ='Research Log'!B5 -> Dog Calming Spray | D16: ='Research Log'!D5 -> Shopify | E16: ='Research Log'!F5 -> 29 | F16: ='Research Log'!I5 -> 0.67241379 | G16: ='Research Log'!J5 -> 1.4871795 | H16: ='Research Log'!L5 -> FAIL
B17: ='Research Log'!A6 -> 2026-04-10 | C17: ='Research Log'!B6 -> Snuffle Mat (Enrichment) | D17: ='Research Log'!D6 -> Amazon UK | E17: ='Research Log'!F6 -> 18 | F17: ='Research Log'!I6 -> 0.55555556 | G17: ='Research Log'!J6 -> 1.8 | H17: ='Research Log'!L6 -> FAIL
B18: ='Research Log'!A7 -> 2026-04-10 | C18: ='Research Log'!B7 -> Premium Lick Mat (Suction Cup Silicone) — Single Unit | D18: ='Research Log'!D7 -> AliExpress | E18: ='Research Log'!F7 -> 20 | F18: ='Research Log'!I7 -> 0.6 | G18: ='Research Log'!J7 -> 1.6666667 | H18: ='Research Log'!L7 -> WARN

Sheet Financial Calculator
A1: PAXA Lick Mat — Financial Calculator (Updated April 2026)
A3: INPUTS | B3: Value | D3: OUTPUTS | E3: Result
A4: Selling Price £ (single unit) | B4: 20 | D4: Gross Profit ($) | E4: =B4-B5-B6 -> 12
A5: Product COGS £ (confirmed supplier) | B5: 2.5 | D5: Gross Margin % | E5: =(B4-B5-B6)/B4 -> 0.6
A6: Shipping + Pick/Pack £ (RM Tracked 48 + 3PL) | B6: 5.5 | D6: Break-Even ROAS | E6: =B4/(B4-B5-B6) -> 1.6666667
A7: Returns Buffer (% of revenue) | B7: 0.06 | D7: Net Profit (est.) | E7: =B4-B5-B6-(B4*B7)-(B4*B8)-B9 -> 10.2
A8: Payment Fees (% of revenue) | B8: 0.03 | D8: Net Margin % | E8: =(B4-B5-B6-(B4*B7)-(B4*B8)-B9)/B4 -> 0.51
A9: Ad Spend Estimate ($) | B9: 0 | D9: Target ROAS (20% net) | E9: =IF(B4>0,B4/((B4*0.2)+B5+B6+(B4*B7)+(B4*B8)),"") -> 1.4492754
A11: BENCHMARKS
A12: Gross Margin | B12: ≥ 65% | C12: Good margin for paid ads
A13: Break-Even ROAS | B13: ≤ 2.0x | C13: Profitable at reasonable ad efficiency
A14: Net Margin | B14: 15–25% | C14: Sustainable growth range
A15: Markup on COGS | B15: ≥ 3x | C15: Minimum for ads + returns buffer
A16: ── BUNDLE SCENARIO (2x Mats for £35) ──
A17: BUNDLE INPUTS | B17: Value | D17: BUNDLE OUTPUTS | E17: Result
A18: Bundle Price £ | B18: 35 | D18: Gross Profit £ | E18: =B18-B19-B20 -> 24.5
A19: Bundle COGS £ (2x £2.50) | B19: 5 | D19: Gross Margin % | E19: =(B18-B19-B20)/B18 -> 0.7
A20: Shipping + Pick/Pack £ (same as single) | B20: 5.5 | D20: Break-Even ROAS | E20: =B18/(B18-B19-B20) -> 1.4285714
A21: Max CPA (break-even) £ | B21: =B18-B19-B20 -> 24.5 | D21: Net Margin % (no ads) | E21: =(B18-B19-B20-(B18*0.06)-(B18*0.03))/B18 -> 0.61
A23: ── UK AD BENCHMARKS (Gemini Research, April 2026) ──
A24: Metric | B24: TikTok Shop / Ads | C24: Meta (FB+IG) | D24: Viable at £35 Bundle?
A25: CPM (UK pet niche) | B25: £8 – £10 | C25: £10 – £15 | D25: —
A26: CPC | B26: £0.60 – £0.90 | C26: £0.80 – £1.20 | D26: —
A27: Conversion Rate | B27: 1.5% – 3.0% | C27: 2.0% – 4.0% | D27: —
A28: Est. CPA | B28: £6 – £9 | C28: £8 – £12 | D28: Yes — max CPA is £24.50
A29: Min. Daily Budget | B29: £20/day | C29: £10/ad set | D29: —
A30: ROAS Weeks 1–3 | B30: — | C30: 1.5x – 2.2x | D30: BE ROAS is 1.43x ✓
A31: TikTok Creator Commission | B31: 15–20% = £5.25–7 | C31: — | D31: Yes — still profitable
A32: Profit per sale at avg CPA | B32: £15.50 – £18.50 | C32: £12.50 – £16.50 | D32: ✓ Healthy at bundle price
